ldict/__init__.py
ldict/core/__init__.py
ldict/core/appearance.py
ldict/core/base.py
ldict/core/inspection.py
ldict/core/ldict_.py
ldict/core/rshift.py
ldict/customjson.py
ldict/empty.py
ldict/exception.py
ldict/frozenlazydict.py
ldict/lazyval.py
ldict/parameter/__init__.py
ldict/parameter/abslet.py
ldict/parameter/functionspace.py
ldict/parameter/let.py
ldict-3.220128.4.dist-info/METADATA
ldict-3.220128.4.dist-info/WHEEL
ldict-3.220128.4.dist-info/RECORD
