Metadata-Version: 2.1
Name: ldict
Version: 3.220128.4
Summary: Lazy dict
License: GPL
Author: davips
Author-email: dpsabc@gmail.com
Requires-Python: >=3.8,<3.10
Classifier: License :: Other/Proprietary License
Classifier: Programming Language :: Python :: 3
Classifier: Programming Language :: Python :: 3.8
Classifier: Programming Language :: Python :: 3.9
Provides-Extra: full
Requires-Dist: dill (>=0.3.4,<0.4.0) ; extra == "full"
Requires-Dist: lange (>=0.220727.11,<0.220728.0)
Requires-Dist: pandas (>=1.3.3,<2.0.0) ; extra == "full"
Requires-Dist: uncompyle6 (>=3.7.4,<4.0.0)
